{
    "heroes": [
        {
            "name": "Barbarian King",
            "maxLevels": [
                0,
                0,
                0,
                0,
                0,
                0,
                5,
                10,
                30,
                40,
                50,
                65,
                75,
                80,
                85
            ]
        },
        {
            "name": "Archer Queen",
            "maxLevels": [
                0,
                0,
                0,
                0,
                0,
                0,
                0,
                0,
                30,
                40,
                50,
                65,
                75,
                80,
                85
            ]
        },
        {
            "name": "Grand Warden",
            "maxLevels": [
                0,
                0,
                0,
                0,
                0,
                0,
                0,
                0,
                0,
                0,
                20,
                40,
                50,
                55,
                60
            ]
        },
        {
            "name": "Royal Champion",
            "maxLevels": [
                0,
                0,
                0,
                0,
                0,
                0,
                0,
                0,
                0,
                0,
                0,
                0,
                25,
                30,
                35
            ]
        }
    ],
    "pets": [
        {
            "name": "L.A.S.S.I",
            "maxLevels": [
                0,
                0,
                0,
                0,
                0,
                0,
                0,
                0,
                0,
                0,
                0,
                0,
                0,
                10,
                10
            ]
        },
        {
            "name": "Mighty Yak",
            "maxLevels": [
                0,
                0,
                0,
                0,
                0,
                0,
                0,
                0,
                0,
                0,
                0,
                0,
                0,
                10,
                10
            ]
        },
        {
            "name": "Electro Owl",
            "maxLevels": [
                0,
                0,
                0,
                0,
                0,
                0,
                0,
                0,
                0,
                0,
                0,
                0,
                0,
                10,
                10
            ]
        },
        {
            "name": "Unicorn",
            "maxLevels": [
                0,
                0,
                0,
                0,
                0,
                0,
                0,
                0,
                0,
                0,
                0,
                0,
                0,
                10,
                10
            ]
        },
        {
            "name": "Frosty",
            "maxLevels": [
                0,
                0,
                0,
                0,
                0,
                0,
                0,
                0,
                0,
                0,
                0,
                0,
                0,
                0,
                10
            ]
        },
        {
            "name": "Diggy",
            "maxLevels": [
                0,
                0,
                0,
                0,
                0,
                0,
                0,
                0,
                0,
                0,
                0,
                0,
                0,
                0,
                10
            ]
        },
        {
            "name": "Poison Lizard",
            "maxLevels": [
                0,
                0,
                0,
                0,
                0,
                0,
                0,
                0,
                0,
                0,
                0,
                0,
                0,
                0,
                10
            ]
        },
        {
            "name": "Phoenix",
            "maxLevels": [
                0,
                0,
                0,
                0,
                0,
                0,
                0,
                0,
                0,
                0,
                0,
                0,
                0,
                0,
                10
            ]
        }
    ],
    "troops": [
        {
            "name": "Barbarian",
            "superTroop": "Super Barbarian",
            "maxLevels": [
                1,
                1,
                2,
                2,
                3,
                3,
                4,
                5,
                6,
                7,
                8,
                9,
                9,
                10,
                11
            ]
        },
        {
            "name": "Archer",
            "superTroop": "Super Archer",
            "maxLevels": [
                0,
                1,
                2,
                2,
                3,
                3,
                4,
                5,
                6,
                7,
                8,
                9,
                9,
                10,
                11
            ]
        },
        {
            "name": "Giant",
            "superTroop": "Super Giant",
            "maxLevels": [
                0,
                1,
                1,
                2,
                2,
                3,
                4,
                5,
                6,
                7,
                8,
                9,
                10,
                10,
                11
            ]
        },
        {
            "name": "Goblin",
            "superTroop": "Sneaky Goblin",
            "maxLevels": [
                0,
                1,
                2,
                2,
                3,
                3,
                4,
                5,
                6,
                7,
                7,
                8,
                8,
                8,
                8
            ]
        },
        {
            "name": "Wall Breaker",
            "superTroop": "Super Wall Breaker",
            "maxLevels": [
                0,
                0,
                1,
                2,
                2,
                3,
                4,
                5,
                5,
                6,
                7,
                8,
                9,
                10,
                11
            ]
        },
        {
            "name": "Balloon",
            "superTroop": "Rocket Balloon",
            "maxLevels": [
                0,
                0,
                0,
                2,
                2,
                3,
                4,
                5,
                6,
                6,
                7,
                8,
                9,
                10,
                10
            ]
        },
        {
            "name": "Wizard",
            "superTroop": "Super Wizard",
            "maxLevels": [
                0,
                0,
                0,
                0,
                2,
                3,
                4,
                5,
                6,
                7,
                8,
                9,
                10,
                10,
                11
            ]
        },
        {
            "name": "Healer",
            "maxLevels": [
                0,
                0,
                0,
                0,
                0,
                1,
                2,
                3,
                4,
                4,
                5,
                5,
                6,
                7,
                7
            ]
        },
        {
            "name": "Dragon",
            "superTroop": "Super Dragon",
            "maxLevels": [
                0,
                0,
                0,
                0,
                0,
                0,
                2,
                3,
                4,
                5,
                6,
                7,
                8,
                9,
                9
            ]
        },
        {
            "name": "P.E.K.K.A",
            "maxLevels": [
                0,
                0,
                0,
                0,
                0,
                0,
                0,
                3,
                4,
                6,
                7,
                8,
                9,
                9,
                9
            ]
        },
        {
            "name": "Baby Dragon",
            "superTroop": "Inferno Dragon",
            "maxLevels": [
                0,
                0,
                0,
                0,
                0,
                0,
                0,
                0,
                2,
                4,
                5,
                6,
                7,
                8,
                8
            ]
        },
        {
            "name": "Miner",
            "superTroop": "Super Miner",
            "maxLevels": [
                0,
                0,
                0,
                0,
                0,
                0,
                0,
                0,
                0,
                3,
                5,
                6,
                7,
                8,
                9
            ]
        },
        {
            "name": "Electro Dragon",
            "maxLevels": [
                0,
                0,
                0,
                0,
                0,
                0,
                0,
                0,
                0,
                0,
                2,
                3,
                4,
                5,
                6
            ]
        },
        {
            "name": "Yeti",
            "maxLevels": [
                0,
                0,
                0,
                0,
                0,
                0,
                0,
                0,
                0,
                0,
                0,
                2,
                3,
                4,
                4
            ]
        },
        {
            "name": "Dragon Rider",
            "maxLevels": [
                0,
                0,
                0,
                0,
                0,
                0,
                0,
                0,
                0,
                0,
                0,
                0,
                2,
                3,
                3
            ]
        },
        {
            "name": "Electro Titan",
            "maxLevels": [
                0,
                0,
                0,
                0,
                0,
                0,
                0,
                0,
                0,
                0,
                0,
                0,
                0,
                2,
                3
            ]
        },
        {
            "name": "Minion",
            "superTroop": "Super Minion",
            "maxLevels": [
                0,
                0,
                0,
                0,
                0,
                0,
                2,
                4,
                5,
                6,
                7,
                8,
                9,
                10,
                11
            ]
        },
        {
            "name": "Hog Rider",
            "superTroop": "Super Hog Rider",
            "maxLevels": [
                0,
                0,
                0,
                0,
                0,
                0,
                2,
                4,
                5,
                6,
                7,
                9,
                10,
                11,
                11
            ]
        },
        {
            "name": "Valkyrie",
            "superTroop": "Super Valkyrie",
            "maxLevels": [
                0,
                0,
                0,
                0,
                0,
                0,
                0,
                2,
                4,
                5,
                6,
                7,
                8,
                9,
                9
            ]
        },
        {
            "name": "Golem",
            "maxLevels": [
                0,
                0,
                0,
                0,
                0,
                0,
                0,
                2,
                4,
                5,
                7,
                9,
                10,
                11,
                12
            ]
        },
        {
            "name": "Witch",
            "superTroop": "Super Witch",
            "maxLevels": [
                0,
                0,
                0,
                0,
                0,
                0,
                0,
                0,
                2,
                3,
                4,
                5,
                5,
                5,
                6
            ]
        },
        {
            "name": "Lava Hound",
            "superTroop": "Ice Hound",
            "maxLevels": [
                0,
                0,
                0,
                0,
                0,
                0,
                0,
                0,
                2,
                3,
                4,
                5,
                6,
                6,
                6
            ]
        },
        {
            "name": "Bowler",
            "superTroop": "Super Bowler",
            "maxLevels": [
                0,
                0,
                0,
                0,
                0,
                0,
                0,
                0,
                0,
                2,
                3,
                4,
                5,
                6,
                6
            ]
        },
        {
            "name": "Ice Golem",
            "maxLevels": [
                0,
                0,
                0,
                0,
                0,
                0,
                0,
                0,
                0,
                0,
                3,
                5,
                5,
                6,
                6
            ]
        },
        {
            "name": "Headhunter",
            "maxLevels": [
                0,
                0,
                0,
                0,
                0,
                0,
                0,
                0,
                0,
                0,
                0,
                2,
                3,
                3,
                3
            ]
        },
        {
            "name": "Apprentice Warden",
            "maxLevels": [
                0,
                0,
                0,
                0,
                0,
                0,
                0,
                0,
                0,
                0,
                0,
                0,
                2,
                3,
                4
            ]
        }
    ],
    "spells": [
        {
            "name": "Lightning Spell",
            "maxLevels": [
                0,
                0,
                0,
                0,
                4,
                4,
                4,
                5,
                6,
                7,
                8,
                9,
                9,
                9,
                10
            ]
        },
        {
            "name": "Healing Spell",
            "maxLevels": [
                0,
                0,
                0,
                0,
                0,
                3,
                4,
                5,
                6,
                7,
                7,
                7,
                8,
                8,
                9
            ]
        },
        {
            "name": "Rage Spell",
            "maxLevels": [
                0,
                0,
                0,
                0,
                0,
                0,
                4,
                5,
                5,
                5,
                5,
                6,
                6,
                6,
                6
            ]
        },
        {
            "name": "Jump Spell",
            "maxLevels": [
                0,
                0,
                0,
                0,
                0,
                0,
                0,
                0,
                2,
                3,
                3,
                3,
                4,
                4,
                5
            ]
        },
        {
            "name": "Freeze Spell",
            "maxLevels": [
                0,
                0,
                0,
                0,
                0,
                0,
                0,
                0,
                2,
                5,
                6,
                7,
                7,
                7,
                7
            ]
        },
        {
            "name": "Clone Spell",
            "maxLevels": [
                0,
                0,
                0,
                0,
                0,
                0,
                0,
                0,
                0,
                3,
                5,
                5,
                6,
                7,
                7
            ]
        },
        {
            "name": "Invisibility Spell",
            "maxLevels": [
                0,
                0,
                0,
                0,
                0,
                0,
                0,
                0,
                0,
                0,
                2,
                3,
                4,
                4,
                4
            ]
        },
        {
            "name": "Recall Spell",
            "maxLevels": [
                0,
                0,
                0,
                0,
                0,
                0,
                0,
                0,
                0,
                0,
                0,
                0,
                2,
                3,
                4
            ]
        },
        {
            "name": "Poison Spell",
            "maxLevels": [
                0,
                0,
                0,
                0,
                0,
                0,
                0,
                2,
                3,
                4,
                5,
                6,
                7,
                8,
                9
            ]
        },
        {
            "name": "Earthquake Spell",
            "maxLevels": [
                0,
                0,
                0,
                0,
                0,
                0,
                0,
                2,
                3,
                4,
                5,
                5,
                5,
                5,
                5
            ]
        },
        {
            "name": "Haste Spell",
            "maxLevels": [
                0,
                0,
                0,
                0,
                0,
                0,
                0,
                0,
                2,
                4,
                5,
                5,
                5,
                5,
                5
            ]
        },
        {
            "name": "Skeleton Spell",
            "maxLevels": [
                0,
                0,
                0,
                0,
                0,
                0,
                0,
                0,
                1,
                3,
                4,
                6,
                7,
                7,
                7
            ]
        },
        {
            "name": "Bat Spell",
            "maxLevels": [
                0,
                0,
                0,
                0,
                0,
                0,
                0,
                0,
                0,
                3,
                4,
                5,
                5,
                5,
                6
            ]
        }
    ],
    "siegeMachines": [
        {
            "name": "Wall Wrecker",
            "maxLevels": [
                0,
                0,
                0,
                0,
                0,
                0,
                0,
                0,
                0,
                0,
                0,
                3,
                4,
                4,
                4
            ]
        },
        {
            "name": "Battle Blimp",
            "maxLevels": [
                0,
                0,
                0,
                0,
                0,
                0,
                0,
                0,
                0,
                0,
                0,
                3,
                4,
                4,
                4
            ]
        },
        {
            "name": "Stone Slammer",
            "maxLevels": [
                0,
                0,
                0,
                0,
                0,
                0,
                0,
                0,
                0,
                0,
                0,
                3,
                4,
                4,
                4
            ]
        },
        {
            "name": "Siege Barracks",
            "maxLevels": [
                0,
                0,
                0,
                0,
                0,
                0,
                0,
                0,
                0,
                0,
                0,
                0,
                4,
                4,
                4
            ]
        },
        {
            "name": "Log Launcher",
            "maxLevels": [
                0,
                0,
                0,
                0,
                0,
                0,
                0,
                0,
                0,
                0,
                0,
                0,
                4,
                4,
                4
            ]
        },
        {
            "name": "Flame Flinger",
            "maxLevels": [
                0,
                0,
                0,
                0,
                0,
                0,
                0,
                0,
                0,
                0,
                0,
                0,
                0,
                4,
                4
            ]
        },
        {
            "name": "Battle Drill",
            "maxLevels": [
                0,
                0,
                0,
                0,
                0,
                0,
                0,
                0,
                0,
                0,
                0,
                0,
                0,
                0,
                4
            ]
        }
    ]
}
